ft300python/__init__.py
ft300python/ft300_modbusrtu.py
ft300python/ft300_stream.py
ft300python-1.0.2.dist-info/LICENSE
ft300python-1.0.2.dist-info/METADATA
ft300python-1.0.2.dist-info/WHEEL
ft300python-1.0.2.dist-info/top_level.txt
ft300python-1.0.2.dist-info/RECORD
