Metadata-Version: 2.1
Name: ft300python
Version: 1.0.2
Summary: Python module to get sensor values from Robotiq FT300
Author-email: hygradme <hygradme@gmail.com>
License: MIT License        
Project-URL: Homepage, https://github.com/hygradme/ft300python
Classifier: License :: OSI Approved :: MIT License
Classifier: Programming Language :: Python
Classifier: Programming Language :: Python :: 3
Requires-Python: >=3.6
License-File: LICENSE
Requires-Dist: pyserial
Requires-Dist: pymodbus
